README.rst
setup.cfg
setup.py
nsot_sync/__init__.py
nsot_sync/cli.py
nsot_sync/common.py
nsot_sync.egg-info/PKG-INFO
nsot_sync.egg-info/SOURCES.txt
nsot_sync.egg-info/dependency_links.txt
nsot_sync.egg-info/entry_points.txt
nsot_sync.egg-info/requires.txt
nsot_sync.egg-info/top_level.txt
nsot_sync/commands/__init__.py
nsot_sync/commands/facter.py
nsot_sync/commands/simple.py
nsot_sync/drivers/__init__.py
nsot_sync/drivers/base_driver.py
nsot_sync/drivers/facter.py
nsot_sync/drivers/simple.py