Metadata-Version: 1.1
Name: nsot-sync
Version: 0.4.3
Summary: CLI/Driver-based framework to sync resources to NSoT (IPAM)
Home-page: https://github.com/coxley/nsot_sync
Author: Codey Oxley
Author-email: codey.a.oxley+os@gmail.com
License: UNKNOWN
Download-URL: https://github.com/coxley/nsot_sync/tarball/0.4.3
Keywords: networking,ipam,nsot,cmdb,sync,orion,solarwinds,infoblox,ip,address
Platform: UNKNOWN
